batchprocessor/__init__.py
yabp-0.1.1.dist-info/METADATA
yabp-0.1.1.dist-info/WHEEL
yabp-0.1.1.dist-info/top_level.txt
yabp-0.1.1.dist-info/RECORD
